coremsft/__init__.py
coremsft/main 2.py
coremsft-0.2.dist-info/METADATA
coremsft-0.2.dist-info/WHEEL
coremsft-0.2.dist-info/top_level.txt
coremsft-0.2.dist-info/RECORD
