Metadata-Version: 2.4
Name: coremsft
Version: 0.2
Summary: This package is a test package to send information to a webhook
Author: Eran Paldi
Classifier: Programming Language :: Python :: 3
Classifier: License :: OSI Approved :: MIT License
Classifier: Operating System :: OS Independent
Requires-Python: >=3.6
Dynamic: author
Dynamic: classifier
Dynamic: description
Dynamic: description-content-type
Dynamic: requires-python
Dynamic: summary
